CMakeLists.txt
LICENSE
LICENSE.lgpl
MANIFEST.in
Pipfile
README.md
pyproject.toml
setup.cfg
setup.py
docs/ADDING_EXTERN.md
docs/CHANGELOG.md
docs/CONTRIBUTING.md
docs/CONVERTING20.md
docs/CONVERTING21.md
docs/CONVERTING22.md
docs/CreatingPDFs.md
docs/Doxyfile
docs/DoxygenLayout.xml
docs/GooFitLogo.png
docs/README.md
docs/SYSTEM_INSTALL.md
docs/documentation.md
extern/CLI11/.all-contributorsrc
extern/CLI11/.appveyor.yml
extern/CLI11/.clang-format
extern/CLI11/.clang-tidy
extern/CLI11/.cmake-format.yaml
extern/CLI11/.codecov.yml
extern/CLI11/.editorconfig
extern/CLI11/.pre-commit-config.yaml
extern/CLI11/.remarkrc
extern/CLI11/CHANGELOG.md
extern/CLI11/CLI11.CPack.Description.txt
extern/CLI11/CLI11.hpp.in
extern/CLI11/CMakeLists.txt
extern/CLI11/CPPLINT.cfg
extern/CLI11/LICENSE
extern/CLI11/README.md
extern/CLI11/azure-pipelines.yml
extern/CLI11/conanfile.py
extern/CLI11/meson.build
extern/CLI11/meson_options.txt
extern/CLI11/.ci/azure-build.yml
extern/CLI11/.ci/azure-cmake.yml
extern/CLI11/.ci/azure-test.yml
extern/CLI11/.ci/build_doxygen.sh
extern/CLI11/.ci/build_lcov.sh
extern/CLI11/.ci/make_and_test.sh
extern/CLI11/.ci/run_codecov.sh
extern/CLI11/.github/CONTRIBUTING.md
extern/CLI11/.github/dependabot.yml
extern/CLI11/.github/labeler_merged.yml
extern/CLI11/.github/actions/quick_cmake/action.yml
extern/CLI11/.github/workflows/build.yml
extern/CLI11/.github/workflows/pr_merged.yml
extern/CLI11/.github/workflows/tests.yml
extern/CLI11/book/CMakeLists.txt
extern/CLI11/book/README.md
extern/CLI11/book/SUMMARY.md
extern/CLI11/book/book.json
extern/CLI11/book/chapters/advanced-topics.md
extern/CLI11/book/chapters/an-advanced-example.md
extern/CLI11/book/chapters/basics.md
extern/CLI11/book/chapters/config.md
extern/CLI11/book/chapters/flags.md
extern/CLI11/book/chapters/formatting.md
extern/CLI11/book/chapters/installation.md
extern/CLI11/book/chapters/internals.md
extern/CLI11/book/chapters/options.md
extern/CLI11/book/chapters/subcommands.md
goofit.egg-info/PKG-INFO
goofit.egg-info/SOURCES.txt
goofit.egg-info/dependency_links.txt
goofit.egg-info/requires.txt
goofit.egg-info/top_level.txt
