Metadata-Version: 2.1
Name: goofit
Version: 2.3.0
Summary: GooFit fitting package
Project-URL: Homepage, https://goofit.github.io
Project-URL: Documentation, https://goofit.github.io/GooFit
Project-URL: Bug Tracker, https://github.com/scikit-hep/package/issues
Project-URL: Changelog, https://github.com/GooFit/GooFit/blob/master/docs/CHANGELOG.md
Classifier: Development Status :: 5 - Production/Stable
Classifier: Intended Audience :: Science/Research
Classifier: License :: OSI Approved :: GNU General Public License v3 or later (GPLv3+)
Classifier: License :: OSI Approved :: BSD License
Classifier: Natural Language :: English
Classifier: Operating System :: Unix
Classifier: Programming Language :: C++
Classifier: Programming Language :: Python
Classifier: Programming Language :: Python :: 2
Classifier: Programming Language :: Python :: 2.7
Classifier: Programming Language :: Python :: 3
Classifier: Programming Language :: Python :: 3.6
Classifier: Programming Language :: Python :: 3.7
Classifier: Programming Language :: Python :: 3.8
Classifier: Programming Language :: Python :: 3.9
Classifier: Programming Language :: Python :: 3.10
Classifier: Topic :: Scientific/Engineering :: Physics
Provides: goofit
Requires-Python: !=3.0.*,!=3.1.*,!=3.2.*,!=3.3.*,!=3.4.*,!=3.5.*,>=2.7
Provides-Extra: test
Provides-Extra: dev
License-File: LICENSE
License-File: LICENSE.lgpl
